ascend_cli/__init__.py
ascend_cli/config.py
ascend_cli/files.py
ascend_cli/main.py
ascend_cli/sql.py
ascend_cli/logic/__init__.py
ascend_cli/logic/files_logic.py
ascend_cli/logic/sql_logic.py
ascend_cli-0.1.20.dist-info/METADATA
ascend_cli-0.1.20.dist-info/WHEEL
ascend_cli-0.1.20.dist-info/entry_points.txt
ascend_cli-0.1.20.dist-info/top_level.txt
ascend_cli-0.1.20.dist-info/RECORD
